logstore/__init__.py
logstore/logger.py
logstore-1.0.0.dist-info/LICENSE
logstore-1.0.0.dist-info/METADATA
logstore-1.0.0.dist-info/WHEEL
logstore-1.0.0.dist-info/top_level.txt
logstore-1.0.0.dist-info/RECORD
