Metadata-Version: 2.1
Name: logstore
Version: 1.0.0
Summary: Python log store.
Home-page: https://gitlab.widas.de/cnips/arc-libs/py-logstore
Author: Vicky Tenzin
Author-email: vicky.tenzin@widas.in
Classifier: Programming Language :: Python :: 3
Classifier: License :: OSI Approved :: MIT License
Classifier: Operating System :: OS Independent
Requires-Python: >=3.0
License-File: LICENSE
